djk_ui/__init__.py
djk_ui/conf.py
djk_ui/testing_components.py
djk_ui/tpl.py
djk_ui/widgets.py
djk_ui/jinja2/base_min.htm
djk_ui/jinja2/bs_nav_items.htm
djk_ui/jinja2/bs_range_filter.htm
djk_ui/jinja2/bs_tabs.htm
djk_ui/jinja2/ko_grid.htm
djk_ui/static/djk/css/ui.css
djk_ui/static/djk/css/fonts/glyphicons-halflings-regular.eot
djk_ui/static/djk/css/fonts/glyphicons-halflings-regular.svg
djk_ui/static/djk/css/fonts/glyphicons-halflings-regular.ttf
djk_ui/static/djk/css/fonts/glyphicons-halflings-regular.woff
djk_ui/static/djk/css/fonts/glyphicons-halflings-regular.woff2
djk_ui/static/djk/css/lib/bootstrap-datetimepicker.min.css
djk_ui/static/djk/css/lib/bootstrap-dialog.css
djk_ui/static/djk/css/lib/bootstrap-theme.min.css
djk_ui/static/djk/css/lib/bootstrap.min.css
djk_ui/static/djk/css/lib/bootstrap.min.css.map
djk_ui/static/djk/js/ui.js
djk_ui/static/djk/js/lib/bootstrap-datetimepicker.min.js
djk_ui/static/djk/js/lib/bootstrap-dialog.min.js
djk_ui/static/djk/js/lib/bootstrap.js
djk_ui/static/djk/js/lib/bootstrap.min.js
djk_ui/templates/base_min.html
djk_ui/views/detail_edit.py
djk_ui/views/list.py
djk_bootstrap3-2.2.1.dist-info/LICENSE
djk_bootstrap3-2.2.1.dist-info/METADATA
djk_bootstrap3-2.2.1.dist-info/WHEEL
djk_bootstrap3-2.2.1.dist-info/top_level.txt
djk_bootstrap3-2.2.1.dist-info/RECORD
