Metadata-Version: 2.1
Name: djk-bootstrap3
Version: 2.2.1
Summary: Bootstrap 3 UI for django-jinja-knockout.
Home-page: https://github.com/Dmitri-Sintsov/djk-bootstrap3
Author: Dmitriy Sintsov
Author-email: questpc256@gmail.com
License: LGPL-3.0
Keywords: django,jinja,knockout.js,ajax,forms,grid,datagrid,datatables
Classifier: Development Status :: 4 - Beta
Classifier: Environment :: Web Environment
Classifier: Framework :: Django
Classifier: Intended Audience :: Developers
Classifier: License :: OSI Approved :: BSD License
Classifier: Operating System :: OS Independent
Classifier: Programming Language :: Python :: 3
Classifier: Topic :: Internet :: WWW/HTTP :: Dynamic Content
License-File: LICENSE
